datasets/globalRainfall/dataCrawler.py
finalVersionSphinxDocs/conf.py
geoanalytics/__init__.py
geoanalytics/_repository.py
geoanalytics/analytics.py
geoanalytics/clustering.py
geoanalytics/config.py
geoanalytics/csv2raster.py
geoanalytics/loader.py
geoanalytics/oneclassClassifiers.py
geoanalytics/plotGUI.py
geoanalytics/raster2CSV.py
geoanalytics/repository.py
geoanalytics/scoreCalculator.py
geoanalytics/clustering/AffinityPropagationWrapper.py
geoanalytics/clustering/Agglomerative.py
geoanalytics/clustering/DBScan.py
geoanalytics/clustering/FuzzyCMeans.py
geoanalytics/clustering/Gaussianmixture.py
geoanalytics/clustering/HDBScan.py
geoanalytics/clustering/KMeans.py
geoanalytics/clustering/KMeansPP.py
geoanalytics/clustering/MEANshift.py
geoanalytics/clustering/OpticsClustering.py
geoanalytics/clustering/Spectral.py
geoanalytics/clustering/__init__.py
geoanalytics/conversion/CSV2Parquet.py
geoanalytics/conversion/CSV2Raster.py
geoanalytics/conversion/DF2DB.py
geoanalytics/conversion/Img2Tiff.py
geoanalytics/conversion/LBL2Tiff.py
geoanalytics/conversion/Parquet2CSV.py
geoanalytics/conversion/Pixels2Point.py
geoanalytics/conversion/Point2Pixels.py
geoanalytics/conversion/Raster2CSV.py
geoanalytics/conversion/RasterDF2DB.py
geoanalytics/conversion/__init__.py
geoanalytics/conversion/raster2tsv.py
geoanalytics/datasets/__init__.py
geoanalytics/datasets/avgcube.csv
geoanalytics/extras/__init__.py
geoanalytics/extras/database/__init__.py
geoanalytics/extras/database/repository.py
geoanalytics/extras/neighbours/FindNeighboursUsingEuclidean.py
geoanalytics/extras/neighbours/FindNeighboursUsingGeodesic.py
geoanalytics/extras/neighbours/__init__.py
geoanalytics/extras/visualize/__init__.py
geoanalytics/extras/visualize/visualizePatterns.py
geoanalytics/imputation/BackwardFill.py
geoanalytics/imputation/ForwardFill.py
geoanalytics/imputation/HotDeck.py
geoanalytics/imputation/Interpolation.py
geoanalytics/imputation/KNNImputation.py
geoanalytics/imputation/MICEImputation.py
geoanalytics-2026.1.19.1.dist-info/licenses/LICENSE
geoanalytics-2026.1.19.1.dist-info/METADATA
geoanalytics-2026.1.19.1.dist-info/WHEEL
geoanalytics-2026.1.19.1.dist-info/top_level.txt
geoanalytics-2026.1.19.1.dist-info/RECORD
