Metadata-Version: 2.4
Name: geoanalytics
Version: 2026.1.19.1
Summary: This software is being developed at the University of Aizu, Aizu-Wakamatsu, Fukushima, Japan
Author-email: Rage Uday Kiran <uday.rage@gmail.com>
Maintainer-email: Rage Uday Kiran <uday.rage@gmail.com>
License: GPLv3
Project-URL: Homepage, https://github.com/UdayLab/geoanalytics
Project-URL: Repository, https://github.com/UdayLab/geoanalytics
Project-URL: Bug Tracker, https://github.com/UdayLab/geoanalytics/issues
Keywords: geo,analytics,spatial,postgis,data mining
Classifier: Development Status :: 4 - Beta
Classifier: Programming Language :: Python :: 3
Classifier: License :: OSI Approved :: GNU General Public License v3 (GPLv3)
Classifier: Operating System :: OS Independent
Requires-Python: >=3.5
License-File: LICENSE
Requires-Dist: psutil
Requires-Dist: pandas
Requires-Dist: matplotlib
Requires-Dist: resource
Requires-Dist: validators
Requires-Dist: urllib3
Requires-Dist: psycopg2-binary
Requires-Dist: shapely
Requires-Dist: tqdm
Requires-Dist: mplcursors
Requires-Dist: scikit-learn
Requires-Dist: plotly
Requires-Dist: Pillow
Requires-Dist: numpy
Requires-Dist: sphinx
Requires-Dist: sphinx-rtd-theme
Requires-Dist: validators
Requires-Dist: discord.py
Requires-Dist: networkx
Requires-Dist: deprecated
Requires-Dist: fastparquet
Requires-Dist: numba
Requires-Dist: pami
Requires-Dist: rasterio
Requires-Dist: fancyimpute
Requires-Dist: deprecation
Dynamic: license-file
